{"is_source_file": false, "format": "", "description": "", "external_files": [], "external_methods": [], "published": [], "classes": [], "methods": [], "calls": [], "search-terms": ["CSS", "variables", "theme", "dark", "light", "App", "toggle", "responsive"], "state": 2, "file_id": 5, "knowledge_revision": 16, "git_revision": "27c30f4a884f3c651a7c73bab9fcb2834ebe56ec", "hash": "22f9e17cc1848b56dbb244518ac2707e", "format-version": 4, "code-base-name": "recipe_frontend", "filename": "recipe_frontend/src/App.css", "revision_history": [{"16": "27c30f4a884f3c651a7c73bab9fcb2834ebe56ec"}]}